[
  {
    "Key": 421,
    "Food_Name": "Bagel And Cream Cheese",
    "Img": "https://i.ibb.co/HpFnHXV/breakfast4.png",
    "Description": "How We Dream About Our Future",
    "Price": 6.99
  },
  {
    "Key": 422,
    "Food_Name": "Breakfast Sandwich",
    "Img": "https://i.ibb.co/1rkYc78/breakfast2.png",
    "Description": "How We Dream About Our Future",
    "Price": 9.99
  },
  {
    "Key": 423,
    "Food_Name": "Baked Chiken",
    "Img": "https://i.ibb.co/hXcKW8n/breakfast3.png",
    "Description": "How We Dream About Our Future",
    "Price": 10.99
  },
  {
    "Key": 424,
    "Food_Name": "Eggs Benedict",
    "Img": "https://i.ibb.co/HpFnHXV/breakfast4.png",
    "Description": "How We Dream About Our Future",
    "Price": 8.99
  },
  {
    "Key": 425,
    "Food_Name": "Toast Croissant Fried egg",
    "Img": "https://i.ibb.co/t4HTQ2v/breakfast5.png",
    "Description": "How We Dream About Our Future",
    "Price": 19.99
  },
  {
    "Key": 426,
    "Food_Name": "Full Breakfast Fried Egg Toast Brunch",
    "Img": "https://i.ibb.co/z6ftgpJ/breakfast6.png",
    "Description": "How We Dream About Our Future",
    "Price": 9.99
  }
]